bernstein/__init__.py
bernstein/analysis.py
bernstein/bernstein.py
chebyshev_markov/__init__.py
chebyshev_markov/analysis.py
chebyshev_markov/chebyshev_markov.py
core/__init__.py
core/approximation.py
core/calculation.py
core/integration.py
core/parallel_acceleration.py
utils/__init__.py
utils/compression.py
utils/helpers.py
utils/metrics.py
visualization/__init__.py
visualization/plotting.py
algebraic_fractions_cmb-1.0.0.dist-info/METADATA
algebraic_fractions_cmb-1.0.0.dist-info/WHEEL
algebraic_fractions_cmb-1.0.0.dist-info/top_level.txt
algebraic_fractions_cmb-1.0.0.dist-info/RECORD
