Metadata-Version: 2.4
Name: algebraic-fractions-cmb
Version: 1.0.0
Summary: Аппроксимация и сжатие данных дробями Чебышева–Маркова и Бернштейна
Home-page: https://github.com/Redditask/algebraic-fractions
Author: Artsiom
Author-email: artyomageyko@gmail.com
License: MIT
Classifier: Development Status :: 4 - Beta
Classifier: Intended Audience :: Science/Research
Classifier: License :: OSI Approved :: MIT License
Classifier: Programming Language :: Python :: 3
Classifier: Topic :: Scientific/Engineering :: Mathematics
Requires-Python: >=3.7
Requires-Dist: numpy>=1.20
Requires-Dist: matplotlib>=3.3
Requires-Dist: joblib>=1.0
Dynamic: author
Dynamic: author-email
Dynamic: classifier
Dynamic: description
Dynamic: description-content-type
Dynamic: home-page
Dynamic: license
Dynamic: requires-dist
Dynamic: requires-python
Dynamic: summary
